setup.py
python_cowbull_game/GameController.py
python_cowbull_game/GameMode.py
python_cowbull_game/GameObject.py
python_cowbull_game/__init__.py
python_cowbull_game.egg-info/PKG-INFO
python_cowbull_game.egg-info/SOURCES.txt
python_cowbull_game.egg-info/dependency_links.txt
python_cowbull_game.egg-info/not-zip-safe
python_cowbull_game.egg-info/requires.txt
python_cowbull_game.egg-info/top_level.txt