Metadata-Version: 1.0
Name: python-cowbull-game
Version: 3.1.2
Summary: Python cowbull game object
Home-page: https://github.com/dsandersAzure/python_cowbull_game
Author: David Sanders
Author-email: dsanderscanadanospam@gmail.com
License: Apache License 2.0
Platform: UNKNOWN
